pydendroheatmap/__init__.py
pydendroheatmap/example.py
pydendroheatmap/pydendroheatmap.py
pydendroheatmap-1.5.dist-info/METADATA
pydendroheatmap-1.5.dist-info/RECORD
pydendroheatmap-1.5.dist-info/WHEEL
pydendroheatmap-1.5.dist-info/top_level.txt
