Metadata-Version: 2.1
Name: pydendroheatmap
Version: 1.5
Summary: Tool for creating heatmaps, where rows and columns are organized by hierarchical clusters as seen in http://code.activestate.com/recipes/578175-hierarchical-clustering-heatmap-python/
Home-page: https://github.com/themantalope/pydendroheatmap
Author: Matt Antalek Jr
Author-email: matthew.antalek@northwestern.edu
License: MIT
Platform: UNKNOWN
Classifier: Topic :: Scientific/Engineering :: Visualization
